bento_sts/__init__.py
bento_sts/api/__init__.py
bento_sts/api/routes.py
bento_sts/cli.py
bento_sts/config.py
bento_sts/config_sts/__init__.py
bento_sts/config_sts/query_paths.yml
bento_sts/errors/__init__.py
bento_sts/errors/handlers.py
bento_sts/main/__init__.py
bento_sts/main/forms.py
bento_sts/main/routes.py
bento_sts/mdb.py
bento_sts/mdb_tags.py
bento_sts/mdb_update.py
bento_sts/query/__init__.py
bento_sts/query/_engine.py
bento_sts/query/makeq.py
bento_sts/static/favicon.ico
bento_sts/static/loading.gif
bento_sts/static/sts.css
bento_sts/static/swagger.yaml
bento_sts/sts.py
bento_sts/templates/about-mdb.html
bento_sts/templates/about-sts.html
bento_sts/templates/admin_dashboard.html
bento_sts/templates/base.html
bento_sts/templates/errors/400.html
bento_sts/templates/errors/404.html
bento_sts/templates/errors/500.html
bento_sts/templates/explore.html
bento_sts/templates/index.html
bento_sts/templates/mdb-all-pvs.html
bento_sts/templates/mdb-cde-pvs.html
bento_sts/templates/mdb-model-pvs.html
bento_sts/templates/mdb-model.html
bento_sts/templates/mdb-node-list.html
bento_sts/templates/mdb-node.html
bento_sts/templates/mdb-origin.html
bento_sts/templates/mdb-property.html
bento_sts/templates/mdb-tag.html
bento_sts/templates/mdb-term-tabs.html
bento_sts/templates/mdb-term.html
bento_sts/templates/mdb-valueset.html
bento_sts/templates/mdb.html
bento_sts/templates/reports.html
bento_sts/templates/search.html
bento_sts/templates/swagger-ui.html
bento_sts/templates/version-history-report.html
bento_sts/templates/version-history.html
bento_sts/util.py
bento_sts-0.1.20.dist-info/METADATA
bento_sts-0.1.20.dist-info/WHEEL
bento_sts-0.1.20.dist-info/licenses/LICENSE
bento_sts-0.1.20.dist-info/RECORD
