Metadata-Version: 2.4
Name: bento-sts
Version: 0.1.20
Summary: Bento Simple Terminology Server
License: Apache-2.0
License-File: LICENSE
Author: Mark Benson
Author-email: mark.benson@nih.gov
Maintainer: Mark A. Jensen
Maintainer-email: mark.jensen@nih.gov
Requires-Python: >=3.10
Classifier: Programming Language :: Python :: 3
Classifier: License :: OSI Approved :: Apache Software License
Requires-Dist: Bootstrap-Flask (>=1.5.2)
Requires-Dist: Flask-Moment (>=0.5.2)
Requires-Dist: Flask-Paginate (>=2021.10.29)
Requires-Dist: Flask-WTF (>=0.14.3)
Requires-Dist: Jinja2 (>=2.11.3)
Requires-Dist: MarkupSafe (>=1.1.1)
Requires-Dist: PyYAML (>=5.4.1)
Requires-Dist: WTForms (>=2.1)
Requires-Dist: WTForms-Components (>=0.10.5)
Requires-Dist: Werkzeug (==3.0.6)
Requires-Dist: babel (>=2.17.0,<3.0.0)
Requires-Dist: bento-meta (>=0.2.16,<0.3.0)
Requires-Dist: certifi (>=2025.4.26,<2026.0.0)
Requires-Dist: cryptography (>=45.0.3,<46.0.0)
Requires-Dist: flask (>=2.3.2,<3.0.0)
Requires-Dist: flask-testing (>=0.8.1,<0.9.0)
Requires-Dist: guess-language-spirit (>=0.5.3)
Requires-Dist: gunicorn (>=20.1.0)
Requires-Dist: idna (>=2.6)
Requires-Dist: importlib_resources (>=5.4.0)
Requires-Dist: itsdangerous (>=0.24)
Requires-Dist: jsonschema (<4.11.0)
Requires-Dist: mako (>=1.3.10,<2.0.0)
Requires-Dist: neo4j (>=4.1)
Requires-Dist: pytest (>=8.0.0)
Requires-Dist: pytest-docker (>=3.1.1)
Requires-Dist: pytest-flask (>=1.3.0,<2.0.0)
Requires-Dist: pytest-mock (>=3.14.0,<4.0.0)
Requires-Dist: python-dateutil (>=2.6.1)
Requires-Dist: python-dotenv (>=0.15.0)
Requires-Dist: python-editor (>=1.0.3)
Requires-Dist: pytz (>=2017.2)
Requires-Dist: requests (>=2.32.4)
Requires-Dist: setuptools (>=80.9.0,<81.0.0)
Requires-Dist: six (>=1.15.0)
Requires-Dist: tomli (>=2.0.1) ; python_version < "3.11"
Requires-Dist: tornado (>=6.5.1,<7.0.0)
Requires-Dist: urllib3 (>=2.5.0,<3.0.0)
Requires-Dist: visitor (>=0.1.3)
Project-URL: Bug Tracker, https:/github.com/CBIIT/bento-sts/issues
Project-URL: Homepage, https://github.com/CBIIT/bento-sts
